{
    "1": "host",
    "1-description": "What host would you like to use?",
    "2": "port",
    "2-description": "What port would you like to use?",
    "3": "password",
    "3-description": "What password would you like to use?",
    "4": "keepAlive",
    "4-description": "Enable keepAlive? (true/false)",
    "5": "betaUpdates",
    "5-description": "enable beta updates?",
    "6": "protocol",
    "6-description":"What protocol would you like to use? (tcp/udp)",
    "7": "challenge",
    "7-description": "Would you like to use the challenge protocol? (true/false)",
    "length": "7",
    "options-after":"5"
}